searchcli/__init__.py
searchcli/cli.py
searchcli/engines.py
searchcli/interactive.py
searchcli/search.py
searchcli/utils.py
search_cli_pro-0.1.5.dist-info/METADATA
search_cli_pro-0.1.5.dist-info/WHEEL
search_cli_pro-0.1.5.dist-info/entry_points.txt
search_cli_pro-0.1.5.dist-info/top_level.txt
search_cli_pro-0.1.5.dist-info/RECORD
