Metadata-Version: 2.4
Name: search-cli-pro
Version: 0.1.5
Summary: A simple cross-platform CLI tool to search the web from your terminal
Author-email: Hrishikesh Tiwari <tiwarihrishikesh686@gmail.com>
License: MIT
Keywords: cli,search,browser,google,duckduckgo,bing
Classifier: Programming Language :: Python :: 3
Classifier: Operating System :: OS Independent
Requires-Python: >=3.7
Requires-Dist: requests>=2.31.0
Requires-Dist: beautifulsoup4>=4.12.0
Requires-Dist: InquirerPy>=0.3
Requires-Dist: rich>=13.5.2
